vidoptim/__init__.py
vidoptim/__main__.py
vidoptim/cli.py
vidoptim/convert.py
vidoptim/probe.py
vidoptim/progress.py
vidoptim/schemas/__init__.py
vidoptim/schemas/core.py
vidoptim/schemas/probe.py
vidoptim-0.0.1a4.dist-info/entry_points.txt
vidoptim-0.0.1a4.dist-info/LICENSE
vidoptim-0.0.1a4.dist-info/WHEEL
vidoptim-0.0.1a4.dist-info/METADATA
vidoptim-0.0.1a4.dist-info/RECORD
